mango_calendar/__init__.py
mango_calendar/calendar_features.py
mango_calendar/date_utils.py
mango_calendar/py.typed
mango_calendar/tests/__init__.py
mango_calendar/tests/test_calendar_features.py
mango_calendar/tests/test_date_utils.py
mango_calendar-1.0.0.dist-info/licenses/LICENSE
mango_calendar-1.0.0.dist-info/METADATA
mango_calendar-1.0.0.dist-info/WHEEL
mango_calendar-1.0.0.dist-info/top_level.txt
mango_calendar-1.0.0.dist-info/RECORD
