Metadata-Version: 2.4
Name: mango-calendar
Version: 1.0.0
Summary: Library with a collection of useful classes and methods to DRY
Author-email: baobab soluciones <mango@baobabsoluciones.es>
License: Apache Software License
Project-URL: repository, https://github.com/baobabsoluciones/mango
Classifier: Programming Language :: Python :: 3
Classifier: License :: OSI Approved :: Apache Software License
Classifier: Operating System :: OS Independent
Classifier: Development Status :: 4 - Beta
Requires-Python: >=3.10
License-File: LICENSE
Requires-Dist: holidays>=0.76
Requires-Dist: numpy>=2.2.4
Requires-Dist: pandas>=2.3.1
Requires-Dist: polars>=1.31.0
Requires-Dist: pyarrow>=20.0.0
Requires-Dist: pycountry>=24.6.1
Requires-Dist: unidecode>=1.4.0
Provides-Extra: dev
Requires-Dist: coverage[toml]>=7.0; extra == "dev"
Dynamic: license-file
